{"input":[{"Name":"3","FgColor":"#604A7B","BgColor":"#FFFFFF","ValueType":"","Value":"3","DataType":"Number","HTMLDataType":"number"},{"Name":"Boolean","FgColor":"#000000","BgColor":"#FFFFFF","ValueType":"","Value":"TRUE","DataType":"Logical","HTMLDataType":"checkbox"},{"Name":"CheckNumberRange","FgColor":"#000000","BgColor":"#FFFFFF","ValueType":"WholeNumber","Value":"5","DataType":"Number","HTMLDataType":"number"},{"Name":"ComplexValidation","FgColor":"#006100","BgColor":"#C6EFCE","ValueType":"Custom","Value":"2342","DataType":"Number","HTMLDataType":"number"},{"Name":"DateInput","FgColor":"#000000","BgColor":"#FFFFFF","ValueType":"Date","Value":"2016-06-03","DataType":"Date","HTMLDataType":"date"},{"Name":"FirstInput","FgColor":"#000000","BgColor":"#FFFFFF","ValueType":"","Value":"1","DataType":"Number","HTMLDataType":"number"},{"Name":"WithListofValues","FgColor":"#000000","BgColor":"#FFFFFF","ValueType":"List","Value":"Yellow","DataType":"Text","HTMLDataType":"text"},{"Name":"WithSomeColour","FgColor":"#000000","BgColor":"#FFFF00","ValueType":"","Value":"2","DataType":"Number","HTMLDataType":"number"}]}